README.txt
setup.cfg
setup.py
docs/HISTORY.txt
docs/INSTALL.txt
docs/LICENSE.GPL
docs/LICENSE.txt
my315ok/__init__.py
my315ok/__init__.pyc
my315ok.portlet.flash.egg-info/PKG-INFO
my315ok.portlet.flash.egg-info/SOURCES.txt
my315ok.portlet.flash.egg-info/dependency_links.txt
my315ok.portlet.flash.egg-info/entry_points.txt
my315ok.portlet.flash.egg-info/namespace_packages.txt
my315ok.portlet.flash.egg-info/not-zip-safe
my315ok.portlet.flash.egg-info/paster_plugins.txt
my315ok.portlet.flash.egg-info/requires.txt
my315ok.portlet.flash.egg-info/top_level.txt
my315ok/portlet/__init__.py
my315ok/portlet/__init__.pyc
my315ok/portlet/flash/__init__.py
my315ok/portlet/flash/__init__.pyc
my315ok/portlet/flash/configure.zcml
my315ok/portlet/flash/flashportlet.pt
my315ok/portlet/flash/flashportlet.py
my315ok/portlet/flash/flashportlet.pyc
my315ok/portlet/flash/version.txt
my315ok/portlet/flash/browser/__init__.py
my315ok/portlet/flash/browser/__init__.pyc
my315ok/portlet/flash/browser/configure.zcml
my315ok/portlet/flash/browser/jss/jquery.swfobj.js
my315ok/portlet/flash/browser/jss/jquery.swfobj.min.js
my315ok/portlet/flash/browser/stylesheets/friendly_link.css
my315ok/portlet/flash/locales/my315ok.portlet.flash.pot
my315ok/portlet/flash/locales/zh/LC_MESSAGES/my315ok.portlet.flash.mo
my315ok/portlet/flash/locales/zh/LC_MESSAGES/my315ok.portlet.flash.po
my315ok/portlet/flash/profiles/default/metadata.xml
my315ok/portlet/flash/profiles/default/portlets.xml
my315ok/portlet/flash/tests/__init__.py
my315ok/portlet/flash/tests/base.py
my315ok/portlet/flash/tests/test_portlet.py