Metadata-Version: 1.0
Name: my315ok.portlet.flash
Version: 3.0dev-r332
Summary: a portlet render flash using swfobj.js
Home-page: 315ok.org
Author: adam tang
Author-email: yuejun.tang@gmail.com
License: GPL
Keywords: flash portlet
Platform: UNKNOWN
Classifier: Framework :: Plone
Classifier: Programming Language :: Python
Classifier: Topic :: Software Development :: Libraries :: Python Modules
